gamspy/__init__.py
gamspy/__main__.py
gamspy/_communication.py
gamspy/_config.py
gamspy/_container.py
gamspy/_convert.py
gamspy/_database.py
gamspy/_extrinsic.py
gamspy/_miro.py
gamspy/_model.py
gamspy/_model_instance.py
gamspy/_options.py
gamspy/_serialization.py
gamspy/_types.py
gamspy/_validation.py
gamspy/_workspace.py
gamspy/exceptions.py
gamspy/py.typed
gamspy/utils.py
gamspy/version.py
gamspy/_algebra/__init__.py
gamspy/_algebra/condition.py
gamspy/_algebra/domain.py
gamspy/_algebra/expression.py
gamspy/_algebra/number.py
gamspy/_algebra/operable.py
gamspy/_algebra/operation.py
gamspy/_backend/__init__.py
gamspy/_backend/backend.py
gamspy/_backend/engine.py
gamspy/_backend/local.py
gamspy/_backend/neos.py
gamspy/_cli/__init__.py
gamspy/_cli/cli.py
gamspy/_cli/gdx.py
gamspy/_cli/install.py
gamspy/_cli/list.py
gamspy/_cli/mps2gms.py
gamspy/_cli/probe.py
gamspy/_cli/retrieve.py
gamspy/_cli/run.py
gamspy/_cli/show.py
gamspy/_cli/uninstall.py
gamspy/_cli/util.py
gamspy/_symbols/__init__.py
gamspy/_symbols/alias.py
gamspy/_symbols/equation.py
gamspy/_symbols/parameter.py
gamspy/_symbols/set.py
gamspy/_symbols/symbol.py
gamspy/_symbols/universe_alias.py
gamspy/_symbols/variable.py
gamspy/_symbols/implicits/__init__.py
gamspy/_symbols/implicits/implicit_equation.py
gamspy/_symbols/implicits/implicit_parameter.py
gamspy/_symbols/implicits/implicit_set.py
gamspy/_symbols/implicits/implicit_symbol.py
gamspy/_symbols/implicits/implicit_variable.py
gamspy/formulations/__init__.py
gamspy/formulations/piecewise.py
gamspy/formulations/result.py
gamspy/formulations/shape.py
gamspy/formulations/utils.py
gamspy/formulations/ml/__init__.py
gamspy/formulations/ml/decision_tree_struct.py
gamspy/formulations/ml/gradient_boosting.py
gamspy/formulations/ml/random_forest.py
gamspy/formulations/ml/regression_tree.py
gamspy/formulations/nn/__init__.py
gamspy/formulations/nn/avgpool2d.py
gamspy/formulations/nn/conv1d.py
gamspy/formulations/nn/conv2d.py
gamspy/formulations/nn/linear.py
gamspy-1.18.3.dist-info/licenses/LICENSE
gamspy-1.18.3.dist-info/METADATA
gamspy-1.18.3.dist-info/WHEEL
gamspy-1.18.3.dist-info/entry_points.txt
gamspy-1.18.3.dist-info/top_level.txt
gamspy-1.18.3.dist-info/RECORD
