Metadata-Version: 2.4
Name: gamspy
Version: 1.18.3
Summary: Python-based algebraic modeling interface to GAMS
Author-email: GAMS Development Corporation <support@gams.com>
Project-URL: homepage, https://gams.com/sales/gamspy_facts/
Project-URL: documentation, https://gamspy.readthedocs.io/en/latest/user/index.html
Project-URL: repository, https://github.com/GAMS-dev/gamspy
Project-URL: changelog, https://github.com/GAMS-dev/gamspy/blob/develop/CHANGELOG.md
Keywords: Optimization,GAMS
Classifier: Development Status :: 5 - Production/Stable
Classifier: Environment :: Console
Classifier: Programming Language :: Python
Classifier: Topic :: Software Development
Classifier: Topic :: Scientific/Engineering
Classifier: Intended Audience :: Developers
Classifier: Intended Audience :: Science/Research
Classifier: License :: OSI Approved :: MIT License
Classifier: Programming Language :: Python
Classifier: Programming Language :: Python :: 3
Classifier: Programming Language :: Python :: 3 :: Only
Classifier: Programming Language :: Python :: 3.10
Classifier: Programming Language :: Python :: 3.11
Classifier: Programming Language :: Python :: 3.12
Classifier: Programming Language :: Python :: 3.13
Classifier: Programming Language :: Python :: 3.14
Classifier: Operating System :: POSIX
Classifier: Operating System :: Unix
Classifier: Operating System :: MacOS
Classifier: Operating System :: Microsoft :: Windows
Requires-Python: >=3.10
License-File: LICENSE
Requires-Dist: gamsapi<53.0.0,>=52.2.0
Requires-Dist: gamspy_base<53.0.0,>=52.2.0
Requires-Dist: pandas<2.4,>=2.2.2
Requires-Dist: pydantic>=2.0
Requires-Dist: requests>=2.28.0
Requires-Dist: typer>=0.16.0
Provides-Extra: dev
Requires-Dist: ruff>=0.13.0; extra == "dev"
Requires-Dist: pre-commit>=3.5.0; extra == "dev"
Requires-Dist: mypy>=1.18.1; extra == "dev"
Requires-Dist: griffe>=1.14.0; extra == "dev"
Provides-Extra: test
Requires-Dist: coverage[toml]>=7.2.7; extra == "test"
Requires-Dist: openpyxl>=3.1.2; extra == "test"
Requires-Dist: cerberus>=1.3.5; extra == "test"
Requires-Dist: python-dotenv>=1.0.0; extra == "test"
Requires-Dist: pytest>=8.0.0; extra == "test"
Requires-Dist: networkx>=3.2.1; extra == "test"
Requires-Dist: scikit-learn>=1.6.1; extra == "test"
Provides-Extra: doc
Requires-Dist: sphinx>=7.1.2; extra == "doc"
Requires-Dist: numpydoc>=1.5.0; extra == "doc"
Requires-Dist: nbsphinx>=0.9.3; extra == "doc"
Requires-Dist: sphinx_copybutton>=0.5.2; extra == "doc"
Requires-Dist: sphinx-favicon>=1.0.1; extra == "doc"
Requires-Dist: ipykernel; extra == "doc"
Requires-Dist: matplotlib>=3.7.3; extra == "doc"
Requires-Dist: sphinx_design>=0.5.0; extra == "doc"
Requires-Dist: pydata_sphinx_theme>=0.14.1; extra == "doc"
Requires-Dist: plotly>=5.22.0; extra == "doc"
Requires-Dist: kaleido==0.2.1; extra == "doc"
Requires-Dist: pytest>=8.2.1; extra == "doc"
Requires-Dist: nbmake>=1.5.3; extra == "doc"
Requires-Dist: openpyxl>=3.1.2; extra == "doc"
Requires-Dist: sphinx-tabs>=3.4.7; extra == "doc"
Requires-Dist: towncrier>=24.8.0; extra == "doc"
Requires-Dist: geopandas>=1.1.1; extra == "doc"
Provides-Extra: torch
Requires-Dist: torch>=2.7.0; extra == "torch"
Dynamic: license-file
